pyadsbdb/__init__.py
pyadsbdb/client.py
pyadsbdb-0.1.2.dist-info/licenses/LICENSE
pyadsbdb-0.1.2.dist-info/METADATA
pyadsbdb-0.1.2.dist-info/WHEEL
pyadsbdb-0.1.2.dist-info/top_level.txt
pyadsbdb-0.1.2.dist-info/RECORD
