Metadata-Version: 2.4
Name: pyadsbdb
Version: 0.1.2
Summary: A Python wrapper for the adsbdb API
Home-page: https://github.com/ttheek/pyadsbdb
Author: T.Theekshana
Project-URL: Homepage, https://github.com/ttheek/pyadsbdb
Project-URL: Issues, https://github.com/ttheek/pyadsbdb/issues
Project-URL: Repository, https://github.com/ttheek/pyadsbdb.git
Keywords: api,adsb
Classifier: Programming Language :: Python :: 3
Classifier: Operating System :: OS Independent
Classifier: License :: OSI Approved :: MIT License
Classifier: Natural Language :: English
Requires-Python: >=3.8
License-File: LICENSE
Requires-Dist: requests
Dynamic: home-page
Dynamic: license-file
Dynamic: requires-python
